
{
    "name"             : "Kitchen Sink",
    "description"      : "a stained metal sink",
    "state"            : {
        "states"       : ["visible"],
        "graphs"       : ["switch"]
    },
    "weight"           : 50,
    "value"            : 5,
    "size"             : 30,
    "target_responses" : {
        "take"         : "And do what with it? Nice try."
    },
    "state_responses"  : {
        "on"           : "The sink's tap turns, buy only a sad gurgling sound emerges.",
        "off"          : "The sink's tap is off.",
        "broken"       : "What are you, part of a demolition crew? The sink is dented."
    }
}